LICENSE.md
MANIFEST.in
README.md
setup.cfg
setup.py
fig/__init__.py
fig/impact.ttf
fig/logo_ascii_art.txt
fig/reader.py
fig/text_style.py
fig/utils.py
fig/writer.py
fig/yt_dlp_filename_collector.py
fig/scripts/__init__.py
fig/scripts/fig_cli.py
fig/scripts/fig_download.py
fig_converter.egg-info/PKG-INFO
fig_converter.egg-info/SOURCES.txt
fig_converter.egg-info/dependency_links.txt
fig_converter.egg-info/entry_points.txt
fig_converter.egg-info/requires.txt
fig_converter.egg-info/top_level.txt