Metadata-Version: 2.1
Name: fig-converter
Version: 2.9.7
Summary: A python package and CLI to turn videos into GIFs and vice-versa.
Home-page: https://github.com/dropletOrg/FIG
Author: blahberi, kamoodi
Author-email: droplet.org@gmail.com
License: MIT
Keywords: convert converter video gif fig pyfig figpy python-fig fig-python py-fig fig-py caption text edit editor cli package command command-line gif-convert gif-converter tool gif-tool gif-editor gif-editor-tool
License-File: LICENSE.md
